{"nodes": [{"id": "users_adev_go_src_petrosync_internal_db_notification_log_sql_go", "label": "notification_log.sql.go", "file_type": "code", "source_file": "internal/db/notification_log.sql.go", "source_location": "L1"}, {"id": "db_countnotificationsbytypeandtripparams", "label": "CountNotificationsByTypeAndTripParams", "file_type": "code", "source_file": "internal/db/notification_log.sql.go", "source_location": "L21"}, {"id": "int8", "label": "Int8", "file_type": "code", "source_file": "", "source_location": "", "origin_file": "/Users/adev/go/src/petrosync/internal/db/notification_log.sql.go"}, {"id": "notificationtypet", "label": "NotificationTypeT", "file_type": "code", "source_file": "", "source_location": "", "origin_file": "/Users/adev/go/src/petrosync/internal/db/notification_log.sql.go"}, {"id": "db_queries", "label": "Queries", "file_type": "code", "source_file": "internal/db/notification_log.sql.go", "source_location": "L26"}, {"id": "db_queries_countnotificationsbytypeandtrip", "label": ".CountNotificationsByTypeAndTrip()", "file_type": "code", "source_file": "internal/db/notification_log.sql.go", "source_location": "L26"}, {"id": "context", "label": "Context", "file_type": "code", "source_file": "", "source_location": "", "origin_file": "/Users/adev/go/src/petrosync/internal/db/notification_log.sql.go"}, {"id": "db_insertnotificationparams", "label": "InsertNotificationParams", "file_type": "code", "source_file": "internal/db/notification_log.sql.go", "source_location": "L44"}, {"id": "text", "label": "Text", "file_type": "code", "source_file": "", "source_location": "", "origin_file": "/Users/adev/go/src/petrosync/internal/db/notification_log.sql.go"}, {"id": "db_queries_insertnotification", "label": ".InsertNotification()", "file_type": "code", "source_file": "internal/db/notification_log.sql.go", "source_location": "L59"}, {"id": "notificationlog", "label": "NotificationLog", "file_type": "code", "source_file": "", "source_location": "", "origin_file": "/Users/adev/go/src/petrosync/internal/db/notification_log.sql.go"}, {"id": "db_listnotificationsbyrecipientparams", "label": "ListNotificationsByRecipientParams", "file_type": "code", "source_file": "internal/db/notification_log.sql.go", "source_location": "L96"}, {"id": "db_queries_listnotificationsbyrecipient", "label": ".ListNotificationsByRecipient()", "file_type": "code", "source_file": "internal/db/notification_log.sql.go", "source_location": "L101"}, {"id": "db_queries_listnotificationsbytrip", "label": ".ListNotificationsByTrip()", "file_type": "code", "source_file": "internal/db/notification_log.sql.go", "source_location": "L140"}], "edges": [{"source": "users_adev_go_src_petrosync_internal_db_notification_log_sql_go", "target": "go_pkg_context", "relation": "imports_from", "confidence": "EXTRACTED", "source_file": "internal/db/notification_log.sql.go", "source_location": "L9", "weight": 1.0, "context": "import"}, {"source": "users_adev_go_src_petrosync_internal_db_notification_log_sql_go", "target": "go_pkg_github_com_jackc_pgx_v5_pgtype", "relation": "imports_from", "confidence": "EXTRACTED", "source_file": "internal/db/notification_log.sql.go", "source_location": "L11", "weight": 1.0, "context": "import"}, {"source": "users_adev_go_src_petrosync_internal_db_notification_log_sql_go", "target": "db_countnotificationsbytypeandtripparams", "relation": "contains", "confidence": "EXTRACTED", "source_file": "internal/db/notification_log.sql.go", "source_location": "L21", "weight": 1.0}, {"source": "db_countnotificationsbytypeandtripparams", "target": "int8", "relation": "references", "confidence": "EXTRACTED", "source_file": "internal/db/notification_log.sql.go", "source_location": "L22", "weight": 1.0, "context": "field"}, {"source": "db_countnotificationsbytypeandtripparams", "target": "notificationtypet", "relation": "references", "confidence": "EXTRACTED", "source_file": "internal/db/notification_log.sql.go", "source_location": "L23", "weight": 1.0, "context": "field"}, {"source": "db_queries", "target": "db_queries_countnotificationsbytypeandtrip", "relation": "method", "confidence": "EXTRACTED", "source_file": "internal/db/notification_log.sql.go", "source_location": "L26", "weight": 1.0}, {"source": "db_queries_countnotificationsbytypeandtrip", "target": "context", "relation": "references", "confidence": "EXTRACTED", "source_file": "internal/db/notification_log.sql.go", "source_location": "L26", "weight": 1.0, "context": "parameter_type"}, {"source": "db_queries_countnotificationsbytypeandtrip", "target": "db_countnotificationsbytypeandtripparams", "relation": "references", "confidence": "EXTRACTED", "source_file": "internal/db/notification_log.sql.go", "source_location": "L26", "weight": 1.0, "context": "parameter_type"}, {"source": "users_adev_go_src_petrosync_internal_db_notification_log_sql_go", "target": "db_insertnotificationparams", "relation": "contains", "confidence": "EXTRACTED", "source_file": "internal/db/notification_log.sql.go", "source_location": "L44", "weight": 1.0}, {"source": "db_insertnotificationparams", "target": "int8", "relation": "references", "confidence": "EXTRACTED", "source_file": "internal/db/notification_log.sql.go", "source_location": "L45", "weight": 1.0, "context": "field"}, {"source": "db_insertnotificationparams", "target": "int8", "relation": "references", "confidence": "EXTRACTED", "source_file": "internal/db/notification_log.sql.go", "source_location": "L46", "weight": 1.0, "context": "field"}, {"source": "db_insertnotificationparams", "target": "int8", "relation": "references", "confidence": "EXTRACTED", "source_file": "internal/db/notification_log.sql.go", "source_location": "L48", "weight": 1.0, "context": "field"}, {"source": "db_insertnotificationparams", "target": "notificationtypet", "relation": "references", "confidence": "EXTRACTED", "source_file": "internal/db/notification_log.sql.go", "source_location": "L49", "weight": 1.0, "context": "field"}, {"source": "db_insertnotificationparams", "target": "int8", "relation": "references", "confidence": "EXTRACTED", "source_file": "internal/db/notification_log.sql.go", "source_location": "L52", "weight": 1.0, "context": "field"}, {"source": "db_insertnotificationparams", "target": "text", "relation": "references", "confidence": "EXTRACTED", "source_file": "internal/db/notification_log.sql.go", "source_location": "L53", "weight": 1.0, "context": "field"}, {"source": "db_queries", "target": "db_queries_insertnotification", "relation": "method", "confidence": "EXTRACTED", "source_file": "internal/db/notification_log.sql.go", "source_location": "L59", "weight": 1.0}, {"source": "db_queries_insertnotification", "target": "context", "relation": "references", "confidence": "EXTRACTED", "source_file": "internal/db/notification_log.sql.go", "source_location": "L59", "weight": 1.0, "context": "parameter_type"}, {"source": "db_queries_insertnotification", "target": "db_insertnotificationparams", "relation": "references", "confidence": "EXTRACTED", "source_file": "internal/db/notification_log.sql.go", "source_location": "L59", "weight": 1.0, "context": "parameter_type"}, {"source": "db_queries_insertnotification", "target": "notificationlog", "relation": "references", "confidence": "EXTRACTED", "source_file": "internal/db/notification_log.sql.go", "source_location": "L59", "weight": 1.0, "context": "return_type"}, {"source": "users_adev_go_src_petrosync_internal_db_notification_log_sql_go", "target": "db_listnotificationsbyrecipientparams", "relation": "contains", "confidence": "EXTRACTED", "source_file": "internal/db/notification_log.sql.go", "source_location": "L96", "weight": 1.0}, {"source": "db_listnotificationsbyrecipientparams", "target": "int8", "relation": "references", "confidence": "EXTRACTED", "source_file": "internal/db/notification_log.sql.go", "source_location": "L97", "weight": 1.0, "context": "field"}, {"source": "db_queries", "target": "db_queries_listnotificationsbyrecipient", "relation": "method", "confidence": "EXTRACTED", "source_file": "internal/db/notification_log.sql.go", "source_location": "L101", "weight": 1.0}, {"source": "db_queries_listnotificationsbyrecipient", "target": "context", "relation": "references", "confidence": "EXTRACTED", "source_file": "internal/db/notification_log.sql.go", "source_location": "L101", "weight": 1.0, "context": "parameter_type"}, {"source": "db_queries_listnotificationsbyrecipient", "target": "db_listnotificationsbyrecipientparams", "relation": "references", "confidence": "EXTRACTED", "source_file": "internal/db/notification_log.sql.go", "source_location": "L101", "weight": 1.0, "context": "parameter_type"}, {"source": "db_queries_listnotificationsbyrecipient", "target": "notificationlog", "relation": "references", "confidence": "EXTRACTED", "source_file": "internal/db/notification_log.sql.go", "source_location": "L101", "weight": 1.0, "context": "return_type"}, {"source": "db_queries", "target": "db_queries_listnotificationsbytrip", "relation": "method", "confidence": "EXTRACTED", "source_file": "internal/db/notification_log.sql.go", "source_location": "L140", "weight": 1.0}, {"source": "db_queries_listnotificationsbytrip", "target": "context", "relation": "references", "confidence": "EXTRACTED", "source_file": "internal/db/notification_log.sql.go", "source_location": "L140", "weight": 1.0, "context": "parameter_type"}, {"source": "db_queries_listnotificationsbytrip", "target": "int8", "relation": "references", "confidence": "EXTRACTED", "source_file": "internal/db/notification_log.sql.go", "source_location": "L140", "weight": 1.0, "context": "parameter_type"}, {"source": "db_queries_listnotificationsbytrip", "target": "notificationlog", "relation": "references", "confidence": "EXTRACTED", "source_file": "internal/db/notification_log.sql.go", "source_location": "L140", "weight": 1.0, "context": "return_type"}], "raw_calls": [{"caller_nid": "db_queries_countnotificationsbytypeandtrip", "callee": "QueryRow", "is_member_call": true, "source_file": "internal/db/notification_log.sql.go", "source_location": "L27"}, {"caller_nid": "db_queries_countnotificationsbytypeandtrip", "callee": "Scan", "is_member_call": true, "source_file": "internal/db/notification_log.sql.go", "source_location": "L29"}, {"caller_nid": "db_queries_insertnotification", "callee": "QueryRow", "is_member_call": true, "source_file": "internal/db/notification_log.sql.go", "source_location": "L60"}, {"caller_nid": "db_queries_insertnotification", "callee": "Scan", "is_member_call": true, "source_file": "internal/db/notification_log.sql.go", "source_location": "L72"}, {"caller_nid": "db_queries_listnotificationsbyrecipient", "callee": "Query", "is_member_call": true, "source_file": "internal/db/notification_log.sql.go", "source_location": "L102"}, {"caller_nid": "db_queries_listnotificationsbyrecipient", "callee": "Close", "is_member_call": true, "source_file": "internal/db/notification_log.sql.go", "source_location": "L106"}, {"caller_nid": "db_queries_listnotificationsbyrecipient", "callee": "Next", "is_member_call": true, "source_file": "internal/db/notification_log.sql.go", "source_location": "L108"}, {"caller_nid": "db_queries_listnotificationsbyrecipient", "callee": "Scan", "is_member_call": true, "source_file": "internal/db/notification_log.sql.go", "source_location": "L110"}, {"caller_nid": "db_queries_listnotificationsbyrecipient", "callee": "append", "is_member_call": false, "source_file": "internal/db/notification_log.sql.go", "source_location": "L125"}, {"caller_nid": "db_queries_listnotificationsbyrecipient", "callee": "Err", "is_member_call": true, "source_file": "internal/db/notification_log.sql.go", "source_location": "L127"}, {"caller_nid": "db_queries_listnotificationsbytrip", "callee": "Query", "is_member_call": true, "source_file": "internal/db/notification_log.sql.go", "source_location": "L141"}, {"caller_nid": "db_queries_listnotificationsbytrip", "callee": "Close", "is_member_call": true, "source_file": "internal/db/notification_log.sql.go", "source_location": "L145"}, {"caller_nid": "db_queries_listnotificationsbytrip", "callee": "Next", "is_member_call": true, "source_file": "internal/db/notification_log.sql.go", "source_location": "L147"}, {"caller_nid": "db_queries_listnotificationsbytrip", "callee": "Scan", "is_member_call": true, "source_file": "internal/db/notification_log.sql.go", "source_location": "L149"}, {"caller_nid": "db_queries_listnotificationsbytrip", "callee": "append", "is_member_call": false, "source_file": "internal/db/notification_log.sql.go", "source_location": "L164"}, {"caller_nid": "db_queries_listnotificationsbytrip", "callee": "Err", "is_member_call": true, "source_file": "internal/db/notification_log.sql.go", "source_location": "L166"}]}